SumoNetVis/Additionals.py
SumoNetVis/Net.py
SumoNetVis/Trajectory.py
SumoNetVis/_Utils.py
SumoNetVis/__init__.py
SumoNetVis-1.6.2.dist-info/LICENSE.md
SumoNetVis-1.6.2.dist-info/METADATA
SumoNetVis-1.6.2.dist-info/WHEEL
SumoNetVis-1.6.2.dist-info/top_level.txt
SumoNetVis-1.6.2.dist-info/RECORD
