Metadata-Version: 2.1
Name: SumoNetVis
Version: 1.6.2
Summary: A python library to render Sumo network files and trajectories with matplotlib or as an OBJ file.
Home-page: https://github.com/patmalcolm91/SumoNetVis
Author: Patrick Malcolm
Author-email: patmalcolm91@gmail.com
License: MIT
Download-URL: https://github.com/patmalcolm91/SumoNetVis/archive/v1.6.2.tar.gz
Keywords: sumo,network,visualize,plot,matplotlib,traffic
Platform: UNKNOWN
Classifier: Development Status :: 5 - Production/Stable
Classifier: Intended Audience :: Science/Research
Classifier: Topic :: Scientific/Engineering
Classifier: License :: OSI Approved :: MIT License
Classifier: Programming Language :: Python :: 3
Classifier: Programming Language :: Python :: 3.4
Classifier: Programming Language :: Python :: 3.5
Classifier: Programming Language :: Python :: 3.6
Classifier: Programming Language :: Python :: 3.7
Classifier: Programming Language :: Python :: 3.8
Classifier: Programming Language :: Python :: 3.9
Classifier: Programming Language :: Python :: 3.10
Classifier: Programming Language :: Python :: 3.11
Classifier: Programming Language :: Python :: 3.12
Classifier: Programming Language :: Python :: 3.13
Requires-Dist: shapely
Requires-Dist: matplotlib
Requires-Dist: numpy
